Workbook

Sheet Matriz Ckeck LIst
C3: MATRIZ PARA COMPROBACIÓN REQUERIMIENTOS DE CALIDAD DE PROYECTO ACADEMICO
D5: SISTEMA: | E5: Pago Seguro Agrotac
E6: Requerimientos Funcionales
B7: Nº | C7: CRITERIOS DE CALIDAD (Documento/Requerimientos) | E7: Status Nivel de Acuerdo | F7: RF-1: Gestionar acceso al sistema | G7: Status Nivel de Acuerdo | H7: 100 | I7: RF-2: Registrar Comprobante de Pago | J7: Status Nivel de Acuerdo | K7: RF-4: Impotar Datos de Facturación | L7: Status Nivel de Acuerdo | M7: RF-8: Gestionar notificaciones
H8: 0
B9: 1 | C9: Agreed | E9: OK | F9: 1. Videoconferencia de la entrevista 2. Minuta de la entrevista | G9: OK | H9: 1 | I9: 1. Revisión conjunta con el equipo y tutor en videollamada. 2. Minuta del análisis de requisitos y confirmación del alcance funcional. | J9: OK | K9: 1. Videoconferencia de la entrevista 2. Minuta de la entrevista | L9: OK | M9: Videoconferencia de reunión con el cliente Minuta de la entrevista donde se acordó el requisito Documento ADS con la especificación del requisito
B10: 2 | C10: Ranked | E10: OK | F10: 1. El SRS especifica la prioridad del requisito como Obligatorio en la tabla de priorización de requisitos funcionales. | G10: OK | I10: 1. Se especifica como requisito obligatorio y crítico para la operación del sistema, ya que impacta directamente en la gestión financiera y trazabilidad de pagos. | J10: OK | K10: 1. El requisito está priorizado como Obligatorio en la tabla de requisitos funcionales. Además, es importante para actualizar la información de pagos y créditos. | L10: OK | M10: • En la descripción del caso de uso se especifica como requisito crítico para evitar morosidad • Está vinculado a objetivos de negocio relacionados con la gestión de créditos
B11: 3 | C11: Unambiguos | E11: OK | F11: 1. Redacción en lenguaje claro. 2. El tutor y el equipo interpretan de igual manera el caso de uso | G11: OK | I11: 1. El lenguaje es claro y evita ambigüedades. 2. El equipo y el tutor interpretan el mismo flujo del caso de uso (registro, validación, acuse). | J11: OK | K11: 1. Redacción en lenguaje claro. 2. El tutor y el equipo interpretan de igual manera el caso de uso | L11: OK | M11: • Redacción clara usando términos específicos: 'fecha límite', 'vencimiento', 'notificación' • El tutor y el equipo interpretan de igual manera el caso de uso • Flujo de secuencia bien definido sin ambigüedades
B12: 4 | C12: Valid and up-to date | E12: OK | F12: 1. Toda nueva información ha sido incorporada, se han incorporado los últimos cambios pedidos luego del feedback realizado por el cliente | G12: NOK | I12: 1. Faltan incorporar observaciones recientes del cliente respecto a la validación automática con bancos o pasarelas de pago. | J12: NOK | K12: 1. No se han incorporado los últimos cambios cambios tras el feedback realizado por el cliente | L12: NOK | M12: 1. No se han incorporado los últimos cambios cambios tras el feedback realizado por el cliente
B13: 5 | C13: Correct | E13: OK | F13: 1. Está alineado con los objetivos del sistema. 2. Refleja lo que realmente necesita el cliente. | G13: OK | I13: 1. Está alineado con los objetivos O-5 (Evitar errores de registro) y O-7 (Trazabilidad de comprobantes). 2. Representa una necesidad real del proceso contable. | J13: OK | K13: 1. Está alineado con los objetivos del sistema. 2. Refleja lo que realmente necesita el cliente. | L13: OK | M13: • Alineado con objetivos del sistema de gestión de créditos • Refleja la necesidad real del cliente de prevenir morosidad • Contribuye al objetivo de trazabilidad de pagos
B14: 6 | C14: Consisten | E14: OK | F14: 1. Documentación basada en modelos: Diagrama de Casos de Uso. | G14: OK | I14: 1. El flujo del caso de uso es coherente con los modelos de datos y el Diagrama de Casos de Uso. 2. Mantiene consistencia con RF-3 (Procesar Pagos a Crédito). | J14: OK | K14: 1. Usa términos definidos previamente. 2. Palabras repetitivas. | L14: OK | M14: • Alineado con objetivos del sistema de gestión de créditos • Refleja la necesidad real del cliente de prevenir morosidad • Contribuye al objetivo de trazabilidad de pagos
B15: 7 | C15: Verifiable | E15: NOK | F15: 1. Falta Casos de Prueba | G15: NOK | I15: 1. Aún no se han definido casos de prueba unitarios y de integración para validar duplicados y la generación del acuse. | J15: OK | K15: 1. Se puede probar mediante archivos de entrada (correctos e incorrectos). 2. Se pueden revisar los resultados en la base de datos y en los módulos del sistema. 3. Se puede confirmar la generación de reportes de errores y la confirmación de importación. | L15: NOK | M15: • Faltan casos de prueba específicos para validar la generación automática de notificaciones • No se han definido criterios de aceptación medibles • Falta especificar métricas de verificación
B16: 8 | C16: Realizable | E16: NOK | F16: 1. Funcionalidad tomada en cuenta dentro de la estimación del costo del proyecto 2. No se ha desarrollado | G16: OK | I16: 1. El desarrollo del módulo es técnicamente viable con los recursos actuales (framework, base de datos y arquitectura definidos). 2. Su implementación no requiere infraestructura adicional ni dependencias externas complejas. | J16: OK | K16: 1. Todos los componentes técnicos están dentro del alcance de un desarrollo 2. Falta especificar protocolos y forma de migrar los datos | L16: OK | M16: • Funcionalidad considerada en el presupuesto • Técnicamente viable con los recursos del sistema • Dentro del alcance del desarrollo
B17: 9 | C17: Traceable | E17: OK | F17: 1. Es claro el origen del requisito y sus relaciones con otros requisitos (matriz de trazabilidad cliente/casos de uso y casos de uso/casos de uso) 2. Cuenta con un identificador único | G17: OK | I17: 1. Se encuentra relacionado con O-7 (Trazabilidad) y RNF-05 (Registro y Monitoreo). 2. Incluido en la matriz de trazabilidad entre requerimientos y casos de uso. | J17: OK | K17: 1. Se muestra sus asociaciones con los usuarios en el caso de uso 2. Cuenta con un identificador único 3. Se ve su asociación con otros caso de uso y su trayectoria. | L17: OK | M17: • Identificador único: RF-8.1, RF-8.2, RF-8.1 • Origen claro en entrevista con cliente • Asociado a RNF-06, RNF-09, RNF-10 • Incluido en matriz de trazabilidad requisitos/casos de uso
B18: 10 | C18: Complete | E18: OK | F18: 1. Contiene toda la información necesaria (entradas, salidas, precondiciones, postcondiciones) para entender y diseñar la función. 2. Describe completamente la funcionalidad esperada. | G18: OK | I18: 1. Contiene entradas, validaciones, precondiciones, postcondiciones y actores claramente definidos. 2. Describe adecuadamente las reglas de negocio y los resultados esperados. | J18: OK | K18: 1. No contiene toda la información necesaria como precondiciones o postcondiciones para entender y diseñar la función. | L18: OK | M18: • Contiene entradas: fecha actual, créditos registrados • Salidas definidas: notificación al cliente • Precondiciones y postcondiciones especificadas
B19: 11 | C19: Understandability | E19: OK | F19: 1. Se involucra al cliente 2. Existe glosario de términos | G19: OK | I19: 1. El cliente participó en la definición del flujo y la validación de campos. 2. Existe glosario de términos contables y financieros en el documento de soporte. | J19: NOK | K19: 1. No se aclaran los términos respaldado por un glosario | L19: OK | M19: • Cliente participó en la definición del requisito • Existe glosario de términos del sistema • Lenguaje claro y comprensible para todas las partes • Términos técnicos explicados en documentación

Sheet LISTA COMPROBACION RF-1
B1: SISTEMA: | C1: Pago Seguro Agrotac
B2: FECHA: | C2: 46296
B3: AUTOR: | C3: César Luis Galarza Villalva
B4: REQUERIMIENTOS EVALUADOS : | C4: RF-1: Gestionar acceso al sistema
A6: CONTENIDO
A7: No. | B7: Pregunta | C7: SI | D7: NO
A8: 1 | B8: Todos los requerimientos relevantes se han documentado? | C8: X
A9: 2 | B9: Se han implementado las funciones requeridas? | C9: X
A10: 3 | B10: Existe algún mecanismo que permita seguir el impacto de dicho requerimiento a lo largo del resto de las actividades del ciclo productivo.? | C10: X
A11: 4 | B11: El origen de cada requerimento individual está claro ? | C11: X
A12: 5 | B12: Que tan facil es devolverse a los requerimientos? | C12: X
A13: 6 | B13: Los requerimientos reflejan las necesidades y deseos del cliente? | C13: X
A14: 7 | B14: No hay contradicciones entre los requerimientos? | C14: X
A15: 8 | B15: El requerimiento que se esta especificando contribuye a alcanzar un objetivo definido ? | C15: X
A16: 9 | B16: Existe un proceso acotado (en plazo y presupuesto) que permita determinar que el sistema construido satisface lo descrito en el propio requerimiento? | D16: X
A17: SUMATORIA: | C17: =COUNTA('LISTA COMPROBACION RF-1'!$C$8:$C$16) -> 8 | D17: =COUNTA('LISTA COMPROBACION RF-1'!$D$8:$D$16) -> 1
A18: PORCENTAJE : | C18: =C17/9 -> 0.88888889 | D18: =D17/9 -> 0.11111111
A20: DOCUMENTACIÓN
A21: No. | B21: Pregunta | C21: SI | D21: NO
A22: 1 | B22: Aplica un estandar para la documetación de requerimiento? | C22: X
A23: 2 | B23: Cumple con la estructura definida por el estandar? | C23: X
A24: 3 | B24: Utiliza un Glosario de términos normalizado? | C24: X
A25: 4 | B25: Los requerimientos Funcionales estan sujetos a una única interpretación? | D25: X
A26: 5 | B26: El modelo aplicado cumple con la sintaxis? | C26: X
A27: SUMATORIA: | C27: =COUNTA('LISTA COMPROBACION RF-1'!$C$22:$C$26) -> 4 | D27: =COUNTA('LISTA COMPROBACION RF-1'!$D$22:$D$26) -> 1
A28: PORCENTAJE : | C28: =C27/5 -> 0.8 | D28: =D27/5 -> 0.2
A30: NIVEL DE ACUERDO
A31: No. | B31: Pregunta | C31: SI | D31: NO
A32: 1 | B32: Todos los requerimientos han sido acordados con todos los interesados? | C32: X
A33: 2 | B33: Todos los requerimientos modificados han sido acordados por todos los implicados? | C33: X
A34: 3 | B34: Han sido resueltos todos los conflictos conocidos respectos de los requerimientos? | C34: X
A35: SUMATORIA: | C35: =COUNTA('LISTA COMPROBACION RF-1'!$C$32:$C$34) -> 3 | D35: =COUNTA('LISTA COMPROBACION RF-1'!$D$32:$D$34) -> 0
A36: PORCENTAJE : | C36: =C35/3 -> 1 | D36: =D35/3 -> 0
A40: RESUMEN
B41: CONTENIDO | C41: 89
B42: DOCUMENTACIÓN | C42: 80
B43: NIVEL DE ACUERDO | C43: 100

Sheet LISTA COMPROBACION RF-2
B1: SISTEMA: | C1: Pago Seguro Agrotac
B2: FECHA: | C2: 46296
B3: AUTOR: | C3: Uriel Andrade
B4: REQUERIMIENTOS EVALUADOS : | C4: RF-2: Registrar Comprobante de Pago
A6: CONTENIDO
A7: No. | B7: Pregunta | C7: SI | D7: NO
A8: 1 | B8: Todos los requerimientos relevantes se han documentado? | C8: X
A9: 2 | B9: Se han implementado las funciones requeridas? | C9: X
A10: 3 | B10: Existe algún mecanismo que permita seguir el impacto de dicho requerimiento a lo largo del resto de las actividades del ciclo productivo.? | C10: X
A11: 4 | B11: El origen de cada requerimento individual está claro ? | C11: X
A12: 5 | B12: Que tan facil es devolverse a los requerimientos? | C12: X
A13: 6 | B13: Los requerimientos reflejan las necesidades y deseos del cliente? | C13: X
A14: 7 | B14: No hay contradicciones entre los requerimientos? | D14: X
A15: 8 | B15: El requerimiento que se esta especificando contribuye a alcanzar un objetivo definido ? | C15: X
A16: 9 | B16: Existe un proceso acotado (en plazo y presupuesto) que permita determinar que el sistema construido satisface lo descrito en el propio requerimiento? | D16: X
A17: SUMATORIA: | C17: =COUNTA('LISTA COMPROBACION RF-2'!$C$8:$C$16) -> 7 | D17: =COUNTA('LISTA COMPROBACION RF-2'!$D$8:$D$16) -> 2
A18: PORCENTAJE : | C18: =C17/9 -> 0.77777778 | D18: =D17/9 -> 0.22222222
A20: DOCUMENTACIÓN
A21: No. | B21: Pregunta | C21: SI | D21: NO
A22: 1 | B22: Aplica un estandar para la documetación de requerimiento? | C22: X
A23: 2 | B23: Cumple con la estructura definida por el estandar? | C23: X
A24: 3 | B24: Utiliza un Glosario de términos normalizado? | C24: X
A25: 4 | B25: Los requerimientos Funcionales estan sujetos a una única interpretación? | C25: X
A26: 5 | B26: El modelo aplicado cumple con la sintaxis? | C26: X
A27: SUMATORIA: | C27: =COUNTA('LISTA COMPROBACION RF-2'!$C$22:$C$26) -> 5 | D27: =COUNTA('LISTA COMPROBACION RF-2'!$D$22:$D$26) -> 0
A28: PORCENTAJE : | C28: =C27/5 -> 1 | D28: =D27/5 -> 0
A30: NIVEL DE ACUERDO
A31: No. | B31: Pregunta | C31: SI | D31: NO
A32: 1 | B32: Todos los requerimientos han sido acordados con todos los interesados? | D32: X
A33: 2 | B33: Todos los requerimientos modificados han sido acordados por todos los implicados? | D33: X
A34: 3 | B34: Han sido resueltos todos los conflictos conocidos respectos de los requerimientos? | C34: X
A35: SUMATORIA: | C35: =COUNTA('LISTA COMPROBACION RF-2'!$C$32:$C$34) -> 1 | D35: =COUNTA('LISTA COMPROBACION RF-2'!$D$32:$D$34) -> 2
A36: PORCENTAJE : | C36: =C35/3 -> 0.33333333 | D36: =D35/3 -> 0.66666667
A40: RESUMEN
B41: CONTENIDO | C41: 78
B42: DOCUMENTACIÓN | C42: 100
B43: NIVEL DE ACUERDO | C43: 33

Sheet LISTA COMPROBACION RF-4
B1: SISTEMA: | C1: Pago Seguro Agrotac
B2: FECHA: | C2: 46296
B3: AUTOR: | C3: Andy Conteron
B4: REQUERIMIENTOS EVALUADOS : | C4: RF-4: Impotar Datos de Facturación
A6: CONTENIDO
A7: No. | B7: Pregunta | C7: SI | D7: NO
A8: 1 | B8: Todos los requerimientos relevantes se han documentado? | C8: X
A9: 2 | B9: Se han implementado las funciones requeridas? | D9: X
A10: 3 | B10: Existe algún mecanismo que permita seguir el impacto de dicho requerimiento a lo largo del resto de las actividades del ciclo productivo.? | D10: X
A11: 4 | B11: El origen de cada requerimento individual está claro ? | C11: X
A12: 5 | B12: Que tan facil es devolverse a los requerimientos? | C12: X
A13: 6 | B13: Los requerimientos reflejan las necesidades y deseos del cliente? | C13: X
A14: 7 | B14: No hay contradicciones entre los requerimientos? | C14: X
A15: 8 | B15: El requerimiento que se esta especificando contribuye a alcanzar un objetivo definido ? | C15: X
A16: 9 | B16: Existe un proceso acotado (en plazo y presupuesto) que permita determinar que el sistema construido satisface lo descrito en el propio requerimiento? | D16: X
A17: SUMATORIA: | C17: =COUNTA('LISTA COMPROBACION RF-4'!$C$8:$C$16) -> 6 | D17: =COUNTA('LISTA COMPROBACION RF-4'!$D$8:$D$16) -> 3
A18: PORCENTAJE : | C18: =C17/9 -> 0.66666667 | D18: =D17/9 -> 0.33333333
A20: DOCUMENTACIÓN
A21: No. | B21: Pregunta | C21: SI | D21: NO
A22: 1 | B22: Aplica un estandar para la documetación de requerimiento? | C22: X
A23: 2 | B23: Cumple con la estructura definida por el estandar? | C23: X
A24: 3 | B24: Utiliza un Glosario de términos normalizado? | D24: X
A25: 4 | B25: Los requerimientos Funcionales estan sujetos a una única interpretación? | C25: X
A26: 5 | B26: El modelo aplicado cumple con la sintaxis? | C26: X
A27: SUMATORIA: | C27: =COUNTA('LISTA COMPROBACION RF-4'!$C$22:$C$26) -> 4 | D27: =COUNTA('LISTA COMPROBACION RF-4'!$D$22:$D$26) -> 1
A28: PORCENTAJE : | C28: =C27/5 -> 0.8 | D28: =D27/5 -> 0.2
A30: NIVEL DE ACUERDO
A31: No. | B31: Pregunta | C31: SI | D31: NO
A32: 1 | B32: Todos los requerimientos han sido acordados con todos los interesados? | C32: X
A33: 2 | B33: Todos los requerimientos modificados han sido acordados por todos los implicados? | C33: X
A34: 3 | B34: Han sido resueltos todos los conflictos conocidos respectos de los requerimientos? | C34: X
A35: SUMATORIA: | C35: =COUNTA('LISTA COMPROBACION RF-4'!$C$32:$C$34) -> 3 | D35: =COUNTA('LISTA COMPROBACION RF-4'!$D$32:$D$34) -> 0
A36: PORCENTAJE : | C36: =C35/3 -> 1 | D36: =D35/3 -> 0
A40: RESUMEN
B41: CONTENIDO | C41: 67
B42: DOCUMENTACIÓN | C42: 80
B43: NIVEL DE ACUERDO | C43: 100

Sheet LISTA COMPROBACION RF-8
B1: SISTEMA: | C1: Pago Seguro Agrotac
B2: FECHA: | C2: 46296
B3: AUTOR: | C3: Juda Benhur Grijalva Ñacato
B4: REQUERIMIENTOS EVALUADOS : | C4: RF-8: Gestionar notificaciones
A6: CONTENIDO
A7: No. | B7: Pregunta | C7: SI | D7: NO
A8: 1 | B8: Todos los requerimientos relevantes se han documentado? | C8: X
A9: 2 | B9: Se han implementado las funciones requeridas? | D9: X
A10: 3 | B10: Existe algún mecanismo que permita seguir el impacto de dicho requerimiento a lo largo del resto de las actividades del ciclo productivo.? | C10: X
A11: 4 | B11: El origen de cada requerimento individual está claro ? | C11: X
A12: 5 | B12: Que tan facil es devolverse a los requerimientos? | C12: X
A13: 6 | B13: Los requerimientos reflejan las necesidades y deseos del cliente? | C13: X
A14: 7 | B14: No hay contradicciones entre los requerimientos? | C14: X
A15: 8 | B15: El requerimiento que se esta especificando contribuye a alcanzar un objetivo definido ? | C15: X
A16: 9 | B16: Existe un proceso acotado (en plazo y presupuesto) que permita determinar que el sistema construido satisface lo descrito en el propio requerimiento? | C16: X
A17: SUMATORIA: | C17: =COUNTA('LISTA COMPROBACION RF-8'!$C$8:$C$16) -> 8 | D17: =COUNTA('LISTA COMPROBACION RF-8'!$D$8:$D$16) -> 1
A18: PORCENTAJE : | C18: =C17/9 -> 0.88888889 | D18: =D17/9 -> 0.11111111
A20: DOCUMENTACIÓN
A21: No. | B21: Pregunta | C21: SI | D21: NO
A22: 1 | B22: Aplica un estandar para la documetación de requerimiento? | C22: X
A23: 2 | B23: Cumple con la estructura definida por el estandar? | C23: X
A24: 3 | B24: Utiliza un Glosario de términos normalizado? | C24: X
A25: 4 | B25: Los requerimientos Funcionales estan sujetos a una única interpretación? | C25: X
A26: 5 | B26: El modelo aplicado cumple con la sintaxis? | C26: X
A27: SUMATORIA: | C27: =COUNTA('LISTA COMPROBACION RF-8'!$C$22:$C$26) -> 5 | D27: =COUNTA('LISTA COMPROBACION RF-8'!$D$22:$D$26) -> 0
A28: PORCENTAJE : | C28: =C27/5 -> 1 | D28: =D27/5 -> 0
A30: NIVEL DE ACUERDO
A31: No. | B31: Pregunta | C31: SI | D31: NO
A32: 1 | B32: Todos los requerimientos han sido acordados con todos los interesados? | C32: X
A33: 2 | B33: Todos los requerimientos modificados han sido acordados por todos los implicados? | C33: X
A34: 3 | B34: Han sido resueltos todos los conflictos conocidos respectos de los requerimientos? | C34: X
A35: SUMATORIA: | C35: =COUNTA('LISTA COMPROBACION RF-8'!$C$32:$C$34) -> 3 | D35: =COUNTA('LISTA COMPROBACION RF-8'!$D$32:$D$34) -> 0
A36: PORCENTAJE : | C36: =C35/3 -> 1 | D36: =D35/3 -> 0
A40: RESUMEN
B41: CONTENIDO | C41: 89
B42: DOCUMENTACIÓN | C42: 100
B43: NIVEL DE ACUERDO | C43: 100

Sheet RECOMENDACIONES - RF-1
A1: PREGUNTA | B1: RECOMENDACIÓN
A2: ¿Existe un proceso acotado (en plazo y presupuesto) que permita determinar que el sistema construido satisface lo descrito en el propio requerimiento? | B2: Se recomienda establecer un proceso formal de validación y verificación que permita determinar de manera objetiva si el sistema construido satisface lo descrito en los requerimientos del caso de uso “Acceso al sistema”. Este proceso debe estar claramente delimitado en cuanto a tiempo y presupuesto, e incluir actividades específicas de revisión, prueba y validación de los resultados. Asimismo, es necesario definir criterios de aceptación claros y medibles, basados en los requerimientos funcionales y no funcionales, e incorporar pruebas de aceptación por parte de los usuarios finales para confirmar que el sistema responde adecuadamente a sus necesidades. La documentación de los resultados obtenidos, junto con la trazabilidad entre requerimientos, casos de prueba y resultados, permitirá garantizar una adecuada cobertura y control del proceso. Con esta medida, se busca asegurar que el sistema cumpla con los objetivos planteados, minimizando riesgos de incumplimiento, retrabajo y desviaciones en el desarrollo.
A3: ¿Los requerimientos Funcionales estan sujetos a una única interpretación? que permitan medir objetivamente el cumplimiento del requisito? | B3: Se recomienda revisar y reformular los requerimientos funcionales para asegurar que estén redactados de manera clara, precisa y sin ambigüedades, de modo que no den lugar a interpretaciones múltiples. Cada requerimiento debe expresar una sola intención funcional, utilizando un lenguaje técnico consistente y verificable. Es conveniente aplicar técnicas de revisión por pares y validación con los usuarios o responsables del negocio, con el fin de confirmar que todos los involucrados interpretan el requerimiento de la misma manera. Asimismo, se sugiere establecer criterios de aceptación objetivos que permitan comprobar su cumplimiento sin ambigüedad.

Sheet RECOMENDACIONES - RF-2
A1: PREGUNTA | B1: RECOMENDACIÓN
A2: ¿Se han incorporado todos los requerimientos de nivel cero al sistema? | B2: Se recomienda establecer un proceso formal de gestión de cambios que incluya el registro, revisión e incorporación de cada sugerencia recibida por parte del tutor o cliente, asegurando que los requisitos estén siempre actualizados, reflejen las expectativas reales y eviten ambigüedades o malentendidos en etapas posteriores del desarrollo.
A3: ¿Se mantiene la coherencia con otros requisitos del sistema y utiliza términos o definiciones de forma uniforme a lo largo del documento? | B3: Aunque el requisito mantiene coherencia con los demás y utiliza los términos de forma uniforme, se recomienda revisar la redacción para eliminar palabras redundantes que no aportan valor, donde una redacción más concisa mejora la claridad del requisito.
A4: ¿Se han definido criterios de aceptación y casos de prueba que permitan medir objetivamente el cumplimiento del requisito? | B4: Elaborar una lista de Criterios de Aceptación en formato Given-When-Then, asociada a pruebas unitarias o de aceptación automatizadas, de modo que cada criterio quede cubierto por al menos un caso de prueba.
A5: ¿Todos los requerimientos han sido acordados con todos los interesados? | B5: Se recomienda realizar sesiones de validación y consenso con todos los interesados clave antes de cerrar la especificación de requerimientos, esto asegurará que los requerimientos reflejen las necesidades puntuales.

Sheet RECOMENDACIONES - RF-4
A1: PREGUNTA | B1: RECOMENDACIÓN
A2: ¿Existe algún mecanismo que permita seguir el impacto de dicho requerimiento a lo largo del resto de las actividades del ciclo productivo? | B2: Implementar trazabilidad de requerimientos. Esto se logra registrando cada requerimiento en una matriz de trazabilidad, relacionándolo con: Casos de uso, Diseños de módulos, Pruebas, Entregables de desarrollo
A3: ¿Se han definido criterios de aceptación y casos de prueba que permitan medir objetivamente el cumplimiento del requisito? | B3: Para cada requerimiento, definir criterios de aceptación claros y medibles, por ejemplo: El sistema debe permitir crear un usuario en menos de 5 segundos
A4: ¿Existe un proceso acotado que permita determinar que el sistema construido satisface lo descrito en el propio requerimiento? | B4: Implementar un plan de validación y verificación que incluya: Actividades de prueba con fechas y responsables definidos Presupuesto estimado para pruebas y revisiones
A5: ¿Utiliza un Glosario de términos normalizado? | B5: Crear un glosario de términos del proyecto, con definiciones claras y consistentes.

Sheet RECOMENDACIONES - RF-8
A1: PREGUNTA | B1: RECOMENDACIÓN
A2: ¿Existen casos de prueba definidos que permitan verificar el cumplimiento del requisito? | B2: Se debe elaborar un conjunto completo de casos de prueba para cada sub-requisito del RF-8: RF-8.1: Casos de prueba que verifiquen la emisión de notificaciones cuando un crédito alcanza su fecha de vencimiento, incluyendo escenarios con diferentes tipos de créditos y fechas. RF-8.2: Casos de prueba que validen la generación de notificaciones preventivas exactamente 3 días antes del vencimiento, considerando días hábiles, fines de semana y fechas especiales. RF-8.3: Casos de prueba que confirmen la emisión de alertas para pagos vencidos sin abonos registrados, verificando la correcta identificación de deudas morosas.
A3: ¿El requisito ha sido implementado y está funcional en el sistema? | B3: Se recomienda iniciar el proceso de implementación del RF-8 según lo planificado en el presupuesto del proyecto. Es necesario: Asignar los recursos técnicos necesarios para el desarrollo de las tres funcionalidades de notificación (RF-8.1, RF-8.2, RF-8.3). Realizar pruebas unitarias e integrales durante el desarrollo para garantizar el correcto funcionamiento antes del despliegue final. Coordinar con el cliente una demostración del módulo una vez completada la implementación para validar que cumple con sus expectativas.
