Workbook

Sheet Matriz Ckeck LIst
C3: MATRIZ PARA COMPROBACIÓN REQUERIMIENTOS DE CALIDAD DE PROYECTO ACADEMICO
D5: SISTEMA: | E5: Pago Seguro Agrotac
E6: Requerimientos Funcionales
B7: Nº | C7: CRITERIOS DE CALIDAD (Documento/Requerimientos) | E7: Status Nivel de Acuerdo | F7: CU-1: Gestionar acceso al sistema | G7: Status Nivel de Acuerdo | H7: CU-2: Registrar Comprobante de Pago | I7: Status Nivel de Acuerdo | J7: CU-3: Procesar pagos a crédito | K7: Status Nivel de Acuerdo | L7: CU-4: Importar Datos de Facturación | M7: Status Nivel de Acuerdo | N7: CU-5: Gestionar créditos otorgados | O7: Status Nivel de Acuerdo | P7: CU-6: Generar reportes de pagos y créditos | Q7: Status Nivel de Acuerdo | R7: CU-7: Revisar estado de cuenta del cliente | S7: Status Nivel de Acuerdo | T7: CU-8: Gestionar notificaciones
B9: 1 | C9: Agreed | E9: OK | F9: 1. Videoconferencia de la entrevista con el cliente. 2. Minuta de la entrevista y SRS firmado donde se acordó el requisito. | G9: NOK | H9: 1. No existe acta o minuta en la que todos los interesados (Cliente, Asistente y Gerente) aprueben el alcance final del requisito. 2. Queda pendiente acordar si la validación con pasarelas de pago o bancos ('pudiendo integrar') forma parte del alcance. | I9: OK | J9: 1. Videoconferencia de la entrevista con el cliente. 2. Minuta de la entrevista y SRS firmado donde se acordó el requisito. | K9: OK | L9: 1. Videoconferencia de la entrevista con el cliente. 2. Minuta de la entrevista y SRS firmado donde se acordó el requisito. | M9: OK | N9: 1. Videoconferencia de la entrevista con el cliente. 2. Minuta de la entrevista y SRS firmado donde se acordó el requisito. | O9: OK | P9: 1. Videoconferencia de la entrevista con el cliente. 2. Minuta de la entrevista y SRS firmado donde se acordó el requisito. | Q9: OK | R9: 1. Videoconferencia de la entrevista con el cliente. 2. Minuta de la entrevista y SRS firmado donde se acordó el requisito. | S9: OK | T9: 1. Videoconferencia de reunión con el cliente. 2. Minuta de la entrevista donde se acordó el requisito y documento con la especificación.
B10: 2 | C10: Ranked | E10: OK | F10: 1. El SRS especifica la prioridad del requisito como Obligatorio en la tabla de priorización de requisitos funcionales. 2. Es la puerta de entrada al sistema y soporta O-1 (control de acceso seguro). | G10: OK | H10: 1. Se especifica como requisito obligatorio y crítico para la operación del sistema, ya que impacta directamente en la gestión financiera y trazabilidad de pagos. | I10: OK | J10: 1. Requisito de nivel 0 crítico para la operación: actualiza en tiempo real el estado de los créditos. 2. Vinculado directamente al control de cartera de El Granito de AGROTAC. | K10: OK | L10: 1. El requisito está priorizado como Obligatorio en la tabla de requisitos funcionales. Además, es importante para actualizar la información de pagos y créditos. | M10: OK | N10: 1. Requisito de nivel 0 crítico: el otorgamiento y seguimiento de créditos es el núcleo del negocio. 2. Involucra a los actores Gerente y Cliente en el diagrama de nivel 0. | O10: OK | P10: 1. Requisito de nivel 0 importante para la toma de decisiones del gerente y el control de morosidad. 2. Incluye a CU-4 (<<include>>) para disponer de los datos de facturación. | Q10: OK | R10: 1. Requisito de nivel 0 relevante para la transparencia con el cliente: muestra créditos, pagos, cuotas, intereses y saldo. 2. Asociado a O-4 (experiencia de usuario) y O-7 (trazabilidad). | S10: OK | T10: 1. En la descripción del caso de uso se especifica como requisito crítico para evitar morosidad. 2. Está vinculado a objetivos de negocio relacionados con la gestión de créditos.
B11: 3 | C11: Unambiguos | E11: NOK | F11: 1. Se ingresa el 'tipo de usuario', pero también se indica que el cliente se registra por sí mismo y el gerente registra al asistente, sin precisar quién asigna el rol. 2. Se define un código de verificación de seis dígitos, pero no su tiempo de validez ni el número de intentos, lo que admite más de una interpretación. | G11: OK | H11: 1. El lenguaje es claro y evita ambigüedades. 2. El equipo y el tutor interpretan el mismo flujo del caso de uso (registro, validación, acuse). | I11: NOK | J11: 1. Aplica el abono 'según el orden definido por las reglas de negocio', pero esas reglas no se especifican. 2. No se detallan los métodos de pago válidos ni el tratamiento de pagos presenciales frente a pagos en línea. | K11: OK | L11: 1. Redacción en lenguaje claro. 2. El tutor y el equipo interpretan de igual manera el caso de uso. | M11: NOK | N11: 1. La descripción mezcla entradas y procesos ('solicitudes de pago en línea', 'editar planes de pago') sin precisar quién edita el plan ni bajo qué condiciones. 2. No define qué datos componen un crédito otorgado (monto, plazo, interés) ni el contenido del certificado de pago. | O11: NOK | P11: 1. 'Visualizar clientes en riesgo de morosidad' no define el criterio de riesgo (días de mora, monto adeudado). 2. No se precisan filtros ni formatos de salida, y el actor 'Asistente Administrativo' difiere del actor Asistente del diagrama de nivel 0. | Q11: NOK | R11: 1. 'Verificará que la información esté completa y actualizada' no define criterios de completitud ni frecuencia de actualización. 2. No se precisan los 'conceptos' de filtrado ni qué información ve cada actor (Cliente, Asistente, Gerente). | S11: OK | T11: 1. Redacción clara usando términos específicos: 'fecha límite', 'vencimiento', 'notificación'. 2. El tutor y el equipo interpretan de igual manera el caso de uso; flujo de secuencia bien definido.
B12: 4 | C12: Valid and up-to date | E12: OK | F12: 1. Toda nueva información ha sido incorporada en la versión vigente del SRS. 2. Las modificaciones del requisito fueron revisadas y aprobadas por todos los implicados. | G12: NOK | H12: 1. Faltan incorporar observaciones recientes del cliente respecto a la validación automática con bancos o pasarelas de pago. 2. Las modificaciones del requisito no han sido acordadas por todos los implicados. | I12: OK | J12: 1. Toda nueva información ha sido incorporada en la versión vigente del SRS. 2. Las modificaciones del requisito fueron revisadas y aprobadas por todos los implicados. | K12: OK | L12: 1. Se incorporaron los cambios acordados con el cliente (formatos CSV/XLSX e integración con el sistema de facturación de la empresa). 2. Las modificaciones fueron aprobadas por todos los implicados. | M12: OK | N12: 1. Toda nueva información ha sido incorporada en la versión vigente del SRS. 2. Las modificaciones del requisito fueron revisadas y aprobadas por todos los implicados. | O12: OK | P12: 1. Toda nueva información ha sido incorporada en la versión vigente del SRS. 2. Las modificaciones del requisito fueron revisadas y aprobadas por todos los implicados. | Q12: OK | R12: 1. Toda nueva información ha sido incorporada en la versión vigente del SRS. 2. Las modificaciones del requisito fueron revisadas y aprobadas por todos los implicados. | S12: OK | T12: 1. Se incorporaron los cambios acordados con el cliente sobre los avisos de vencimiento y de pago vencido. 2. Las modificaciones fueron aprobadas por todos los implicados.
B13: 5 | C13: Correct | E13: OK | F13: 1. Está alineado con O-1 (control de acceso seguro), O-2 (gestión diferenciada por roles) y O-6 (protección de la información). 2. Refleja lo que realmente necesita el cliente: que cada actor acceda solo a su entorno. | G13: OK | H13: 1. Está alineado con los objetivos O-5 (Evitar errores de registro) y O-7 (Trazabilidad de comprobantes). 2. Representa una necesidad real del proceso: reemplazar el envío de comprobantes por WhatsApp y su registro en Excel. | I13: OK | J13: 1. Está alineado con O-5 (Evitar errores de registro) y O-7 (Trazabilidad de comprobantes). 2. Refleja la necesidad real de aplicar abonos y conocer el saldo actualizado del crédito. | K13: OK | L13: 1. Está alineado con los objetivos del sistema. 2. Refleja lo que realmente necesita el cliente: evitar la digitación manual de facturas. | M13: OK | N13: 1. Está alineado con O-2 (gestión por roles) y O-7 (trazabilidad). 2. Refleja la necesidad del gerente de otorgar créditos y del cliente de consultar condiciones, estado y certificados. | O13: OK | P13: 1. Está alineado con O-7 y O-13 (trazabilidad y auditoría). 2. Responde a la necesidad del gerente de visualizar pagos por cliente, por fechas y clientes en riesgo de morosidad. | Q13: OK | R13: 1. Está alineado con O-4 y O-7. 2. Refleja la necesidad del cliente de conocer su saldo real sin solicitarlo por otros medios. | S13: OK | T13: 1. Alineado con objetivos del sistema de gestión de créditos. 2. Refleja la necesidad real del cliente de prevenir morosidad y contribuye a la trazabilidad de pagos.
B14: 6 | C14: Consisten | E14: OK | F14: 1. Documentación basada en modelos: Diagrama General de Casos de Uso de nivel 0 (actores Cliente, Asistente y Gerente). 2. No presenta contradicciones con los demás requisitos de nivel 0. | G14: NOK | H14: 1. Se solapa con CU-3: ambos asocian el pago a las cuotas, actualizan saldos e intereses y generan un acuse/comprobante con número único. 2. El diagrama de nivel 0 relaciona CU-2 y CU-3 con <<include>>, pero no se delimita dónde termina el registro y dónde inicia el procesamiento del pago. | I14: NOK | J14: 1. Duplica comportamientos de CU-2 (asociación a cuotas, recálculo de saldos e intereses, comprobante con número único). 2. Se superpone con CU-5, cuya descripción también incluye realizar pagos en línea sobre el crédito activo. | K14: OK | L14: 1. Usa términos definidos previamente (factura, cliente, monto, estado del pago). 2. Coherente con el diagrama de nivel 0: CU-6 incluye a CU-4 y participa el actor 'Sistema de facturación de la empresa'. | M14: NOK | N14: 1. Incluye 'editar planes de pago', función que no se desarrolla en la especificación del requisito ni se relaciona con otro caso de uso. 2. 'Realizar pagos en línea' se superpone con CU-2 y CU-3, que ya cubren el registro y procesamiento de pagos. | O14: NOK | P14: 1. La función 'Visualizar auditoría de acciones' asociada a CU-6 en el diagrama no está descrita en su especificación. 2. El diagrama de nivel 0 indica que CU-6 incluye a CU-4 (<<include>>), relación que no se menciona en la descripción del requisito. | Q14: NOK | R14: 1. Se superpone con CU-5 (consulta del estado y condiciones del crédito) y con CU-6 (información de pagos por cliente). 2. No se delimita qué información pertenece al estado de cuenta y cuál a créditos o reportes. | S14: OK | T14: 1. Coherente con CU-5 (créditos y cuotas) y con el diagrama de nivel 0. 2. Usa de forma uniforme los términos vencimiento, cuota y notificación.
B15: 7 | C15: Verifiable | E15: NOK | F15: 1. Falta un proceso acotado (plazo y presupuesto) de verificación y validación. 2. La descripción de nivel 0 no establece criterios de aceptación ni casos de prueba para registro, inicio de sesión y recuperación de contraseña. | G15: NOK | H15: 1. Aún no se han definido casos de prueba ni un plan de validación acotado para carga, duplicados, aprobación, rechazo y asociación del comprobante al pago. | I15: NOK | J15: 1. No se han definido casos de prueba para abonos, cuotas, recálculo de saldos y situaciones excepcionales (crédito inactivo, monto incorrecto). 2. No existe un plan de validación con responsables y fechas. | K15: NOK | L15: 1. Puede probarse con archivos válidos e inválidos, pero no existe un plan de verificación acotado en plazo y presupuesto. 2. Faltan criterios de aceptación medibles para duplicados, inconsistencias y confirmación de importación. | M15: NOK | N15: 1. No se han definido pruebas para otorgamiento de crédito, consultas, pagos asociados ni generación de certificados de pago. 2. Faltan criterios de aceptación medibles para los casos alternos (pagos vencidos, sin créditos activos). | O15: NOK | P15: 1. No existen pruebas para rangos de fechas, clientes sin movimientos, ausencia de morosidad ni resultados vacíos. 2. La descripción no establece criterios de aceptación medibles para cada tipo de reporte. | Q15: NOK | R15: 1. No hay pruebas definidas para el resumen de cuenta, filtros, clientes sin movimientos ni descarga en PDF/XLSX. 2. Falta un plan de validación con responsables y fechas. | S15: OK | T15: 1. Las condiciones de disparo (cuota próxima a vencer, cuota vencida sin pago) son observables y comprobables. 2. Existe un proceso acotado para verificar la emisión de las notificaciones al cliente.
B16: 8 | C16: Realizable | E16: OK | F16: 1. Funcionalidad tomada en cuenta dentro de la estimación del costo del proyecto. 2. Técnicamente viable (autenticación por roles, recuperación por correo) y con evidencia de implementación. | G16: OK | H16: 1. El desarrollo del módulo es técnicamente viable con los recursos actuales (framework, base de datos y arquitectura definidos). 2. Existe evidencia de implementación; la integración con bancos se plantea como opcional. | I16: OK | J16: 1. Técnicamente viable con la arquitectura y base de datos definidas. 2. Pendiente de implementación: no hay evidencia de desarrollo de la aplicación de abonos y actualización de saldos. | K16: OK | L16: 1. Todos los componentes técnicos están dentro del alcance del desarrollo. 2. Pendiente de implementación del módulo; falta especificar protocolos de integración y forma de migrar los datos. | M16: OK | N16: 1. Técnicamente viable con los recursos del proyecto (pasarela de pago, generación de PDF). 2. Pendiente de implementación completa del otorgamiento, consulta y actualización de créditos. | O16: OK | P16: 1. Viable con la base de datos y las librerías de exportación previstas. 2. Pendiente de implementación de los reportes por cliente, fechas y morosidad. | Q16: OK | R16: 1. Viable con los datos de créditos y pagos ya modelados. 2. Pendiente de implementación de la consulta de estado de cuenta. | S16: OK | T16: 1. Funcionalidad considerada en el presupuesto y técnicamente viable (tarea programada y envío de mensajes). 2. Pendiente de implementación de las notificaciones automáticas.
B17: 9 | C17: Traceable | E17: OK | F17: 1. Es claro el origen del requisito y sus relaciones con otros requisitos (matriz de trazabilidad cliente/casos de uso y casos de uso/casos de uso). 2. Cuenta con identificador único CU-1 y se asocia a O-1, O-2 y O-6. | G17: OK | H17: 1. Se encuentra relacionado con O-7 (Trazabilidad) y con el registro y monitoreo del sistema (NF-05). 2. Incluido en la matriz de trazabilidad entre requerimientos y casos de uso. | I17: OK | J17: 1. Cuenta con identificador único CU-3 y relación <<include>> con CU-2 en el diagrama de nivel 0. 2. Origen claro en la entrevista con el cliente y asociado a O-5 y O-7. | K17: NOK | L17: 1. Cuenta con identificador único y origen claro, pero no existe un mecanismo formal que siga su impacto en diseño, implementación y pruebas. 2. No está incorporado en una matriz de trazabilidad origen–SRS–historia de usuario–prueba ni vinculado a RNF. | M17: OK | N17: 1. Identificador único CU-5 con origen claro en la entrevista con el cliente. 2. Relacionado con CU-3 (pagos) y CU-7 (estado de cuenta) dentro del diagrama de nivel 0. | O17: OK | P17: 1. Identificador único CU-6 con origen claro en la entrevista con el cliente. 2. Relación <<include>> con CU-4 en el diagrama de nivel 0 y asociado a O-7 y O-13. | Q17: OK | R17: 1. Identificador único CU-7, con origen en la entrevista y relación con CU-5 y CU-6. 2. Representado en el diagrama de nivel 0 con los actores Cliente y Asistente. | S17: OK | T17: 1. Identificador único CU-8 con origen claro en la entrevista con el cliente. 2. Asociado a los actores Cliente y Gerente en el diagrama de nivel 0 e incluido en la matriz de trazabilidad requisitos/casos de uso.
B18: 10 | C18: Complete | E18: OK | F18: 1. Define entradas (nombre, correo, contraseña, tipo de usuario), proceso (registro, inicio de sesión y recuperación de contraseña) y salida (acceso según rol). 2. Describe completamente la funcionalidad esperada. | G18: OK | H18: 1. Contiene entradas (referencia, fecha, monto, entidad emisora, adjunto), validaciones, actores y salidas (confirmación, estado del crédito, certificado). 2. Describe adecuadamente las reglas de negocio y los resultados esperados. | I18: OK | J18: 1. Define entradas (identificador del crédito, monto, método de pago, fecha y comprobante), validaciones y salidas (comprobante digital y certificado de pago). 2. Describe la funcionalidad esperada a nivel 0. | K18: OK | L18: 1. Contiene entradas (archivo CSV/XLSX o fuente externa), validaciones (formato, duplicados, integridad) y salidas (confirmación y reporte de inconsistencias). 2. Describe completamente la funcionalidad esperada. | M18: OK | N18: 1. Define entradas (solicitudes de pago, consultas de condiciones y estado, solicitudes de certificados), proceso y salidas (información actualizada del crédito y certificados). 2. Describe la funcionalidad esperada a nivel 0. | O18: OK | P18: 1. Define entradas (datos de clientes, rangos de fechas y datos de morosidad) y salidas (reportes de pagos por cliente, por fechas y clientes en riesgo de morosidad). 2. Describe la funcionalidad esperada a nivel 0. | Q18: OK | R18: 1. Define entrada (identificador del cliente o sesión), procesamiento (consulta y orden cronológico) y salida (resumen, filtros y descarga PDF/XLSX). 2. Describe la funcionalidad esperada a nivel 0. | S18: OK | T18: 1. Contiene entradas (fecha actual, créditos y cuotas registradas) y salidas (notificación al cliente). 2. Precondiciones y postcondiciones definidas para el requisito.
B19: 11 | C19: Understandability | E19: OK | F19: 1. Se involucra al cliente en la definición del requisito. 2. Existe glosario de términos normalizado. | G19: OK | H19: 1. El cliente participó en la definición del flujo y la validación de campos. 2. Existe glosario de términos contables y financieros en el documento de soporte. | I19: OK | J19: 1. Se involucra al cliente en la definición del requisito. 2. Existe glosario de términos (crédito, cuota, abono, saldo). | K19: OK | L19: 1. El cliente participó en la definición del requisito. 2. Existe glosario de términos normalizado (factura, importación, inconsistencia). | M19: OK | N19: 1. El cliente participó en la definición del requisito. 2. Existe glosario de términos (crédito activo, cuota, certificado de pago). | O19: OK | P19: 1. El cliente participó en la definición del requisito. 2. Existe glosario de términos (morosidad, días de mora, reporte). | Q19: OK | R19: 1. El cliente participó en la definición del requisito. 2. Existe glosario de términos (estado de cuenta, saldo, interés). | S19: OK | T19: 1. El cliente participó en la definición del requisito. 2. Existe glosario de términos y lenguaje comprensible para todas las partes.

Sheet LISTA COMPROBACION CU-1
B1: SISTEMA: | C1: Pago Seguro Agrotac
B2: FECHA: | C2: 46296
B3: AUTOR: | C3: César Luis Galarza Villalva
B4: REQUERIMIENTOS EVALUADOS : | C4: CU-1: Gestionar acceso al sistema
A6: CONTENIDO
A7: No. | B7: Pregunta | C7: SI | D7: NO
A8: 1 | B8: Todos los requerimientos relevantes se han documentado? | C8: X
A9: 2 | B9: Se han implementado las funciones requeridas? | C9: X
A10: 3 | B10: Existe algún mecanismo que permita seguir el impacto de dicho requerimiento a lo largo del resto de las actividades del ciclo productivo.? | C10: X
A11: 4 | B11: El origen de cada requerimento individual está claro ? | C11: X
A12: 5 | B12: Que tan facil es devolverse a los requerimientos? | C12: X
A13: 6 | B13: Los requerimientos reflejan las necesidades y deseos del cliente? | C13: X
A14: 7 | B14: No hay contradicciones entre los requerimientos? | C14: X
A15: 8 | B15: El requerimiento que se esta especificando contribuye a alcanzar un objetivo definido ? | C15: X
A16: 9 | B16: Existe un proceso acotado (en plazo y presupuesto) que permita determinar que el sistema construido satisface lo descrito en el propio requerimiento? | D16: X
A17: SUMATORIA: | C17: =COUNTA('LISTA COMPROBACION CU-1'!$C$8:$C$16) -> 8 | D17: =COUNTA('LISTA COMPROBACION CU-1'!$D$8:$D$16) -> 1
A18: PORCENTAJE : | C18: =C17/9 -> 0.88888889 | D18: =D17/9 -> 0.11111111
A20: DOCUMENTACIÓN
A21: No. | B21: Pregunta | C21: SI | D21: NO
A22: 1 | B22: Aplica un estandar para la documetación de requerimiento? | C22: X
A23: 2 | B23: Cumple con la estructura definida por el estandar? | C23: X
A24: 3 | B24: Utiliza un Glosario de términos normalizado? | C24: X
A25: 4 | B25: Los requerimientos Funcionales estan sujetos a una única interpretación? | D25: X
A26: 5 | B26: El modelo aplicado cumple con la sintaxis? | C26: X
A27: SUMATORIA: | C27: =COUNTA('LISTA COMPROBACION CU-1'!$C$22:$C$26) -> 4 | D27: =COUNTA('LISTA COMPROBACION CU-1'!$D$22:$D$26) -> 1
A28: PORCENTAJE : | C28: =C27/5 -> 0.8 | D28: =D27/5 -> 0.2
A30: NIVEL DE ACUERDO
A31: No. | B31: Pregunta | C31: SI | D31: NO
A32: 1 | B32: Todos los requerimientos han sido acordados con todos los interesados? | C32: X
A33: 2 | B33: Todos los requerimientos modificados han sido acordados por todos los implicados? | C33: X
A34: 3 | B34: Han sido resueltos todos los conflictos conocidos respectos de los requerimientos? | C34: X
A35: SUMATORIA: | C35: =COUNTA('LISTA COMPROBACION CU-1'!$C$32:$C$34) -> 3 | D35: =COUNTA('LISTA COMPROBACION CU-1'!$D$32:$D$34) -> 0
A36: PORCENTAJE : | C36: =C35/3 -> 1 | D36: =D35/3 -> 0
A40: RESUMEN
B41: CONTENIDO | C41: 89
B42: DOCUMENTACIÓN | C42: 80
B43: NIVEL DE ACUERDO | C43: 100

Sheet LISTA COMPROBACION CU-2
B1: SISTEMA: | C1: Pago Seguro Agrotac
B2: FECHA: | C2: 46296
B3: AUTOR: | C3: Uriel Andrade
B4: REQUERIMIENTOS EVALUADOS : | C4: CU-2: Registrar Comprobante de Pago
A6: CONTENIDO
A7: No. | B7: Pregunta | C7: SI | D7: NO
A8: 1 | B8: Todos los requerimientos relevantes se han documentado? | C8: X
A9: 2 | B9: Se han implementado las funciones requeridas? | C9: X
A10: 3 | B10: Existe algún mecanismo que permita seguir el impacto de dicho requerimiento a lo largo del resto de las actividades del ciclo productivo.? | C10: X
A11: 4 | B11: El origen de cada requerimento individual está claro ? | C11: X
A12: 5 | B12: Que tan facil es devolverse a los requerimientos? | C12: X
A13: 6 | B13: Los requerimientos reflejan las necesidades y deseos del cliente? | C13: X
A14: 7 | B14: No hay contradicciones entre los requerimientos? | D14: X
A15: 8 | B15: El requerimiento que se esta especificando contribuye a alcanzar un objetivo definido ? | C15: X
A16: 9 | B16: Existe un proceso acotado (en plazo y presupuesto) que permita determinar que el sistema construido satisface lo descrito en el propio requerimiento? | D16: X
A17: SUMATORIA: | C17: =COUNTA('LISTA COMPROBACION CU-2'!$C$8:$C$16) -> 7 | D17: =COUNTA('LISTA COMPROBACION CU-2'!$D$8:$D$16) -> 2
A18: PORCENTAJE : | C18: =C17/9 -> 0.77777778 | D18: =D17/9 -> 0.22222222
A20: DOCUMENTACIÓN
A21: No. | B21: Pregunta | C21: SI | D21: NO
A22: 1 | B22: Aplica un estandar para la documetación de requerimiento? | C22: X
A23: 2 | B23: Cumple con la estructura definida por el estandar? | C23: X
A24: 3 | B24: Utiliza un Glosario de términos normalizado? | C24: X
A25: 4 | B25: Los requerimientos Funcionales estan sujetos a una única interpretación? | C25: X
A26: 5 | B26: El modelo aplicado cumple con la sintaxis? | C26: X
A27: SUMATORIA: | C27: =COUNTA('LISTA COMPROBACION CU-2'!$C$22:$C$26) -> 5 | D27: =COUNTA('LISTA COMPROBACION CU-2'!$D$22:$D$26) -> 0
A28: PORCENTAJE : | C28: =C27/5 -> 1 | D28: =D27/5 -> 0
A30: NIVEL DE ACUERDO
A31: No. | B31: Pregunta | C31: SI | D31: NO
A32: 1 | B32: Todos los requerimientos han sido acordados con todos los interesados? | D32: X
A33: 2 | B33: Todos los requerimientos modificados han sido acordados por todos los implicados? | D33: X
A34: 3 | B34: Han sido resueltos todos los conflictos conocidos respectos de los requerimientos? | C34: X
A35: SUMATORIA: | C35: =COUNTA('LISTA COMPROBACION CU-2'!$C$32:$C$34) -> 1 | D35: =COUNTA('LISTA COMPROBACION CU-2'!$D$32:$D$34) -> 2
A36: PORCENTAJE : | C36: =C35/3 -> 0.33333333 | D36: =D35/3 -> 0.66666667
A40: RESUMEN
B41: CONTENIDO | C41: 78
B42: DOCUMENTACIÓN | C42: 100
B43: NIVEL DE ACUERDO | C43: 33

Sheet LISTA COMPROBACION CU-3
B1: SISTEMA: | C1: Pago Seguro Agrotac
B2: FECHA: | C2: 46296
B3: AUTOR: | C3: Uriel Andrade
B4: REQUERIMIENTOS EVALUADOS : | C4: CU-3: Procesar pagos a crédito
A6: CONTENIDO
A7: No. | B7: Pregunta | C7: SI | D7: NO
A8: 1 | B8: Todos los requerimientos relevantes se han documentado? | C8: X
A9: 2 | B9: Se han implementado las funciones requeridas? | D9: x
A10: 3 | B10: Existe algún mecanismo que permita seguir el impacto de dicho requerimiento a lo largo del resto de las actividades del ciclo productivo.? | C10: X
A11: 4 | B11: El origen de cada requerimento individual está claro ? | C11: X
A12: 5 | B12: Que tan facil es devolverse a los requerimientos? | C12: X
A13: 6 | B13: Los requerimientos reflejan las necesidades y deseos del cliente? | C13: X
A14: 7 | B14: No hay contradicciones entre los requerimientos? | D14: X
A15: 8 | B15: El requerimiento que se esta especificando contribuye a alcanzar un objetivo definido ? | C15: X
A16: 9 | B16: Existe un proceso acotado (en plazo y presupuesto) que permita determinar que el sistema construido satisface lo descrito en el propio requerimiento? | D16: X
A17: SUMATORIA: | C17: =COUNTA('LISTA COMPROBACION CU-3'!$C$8:$C$16) -> 6 | D17: =COUNTA('LISTA COMPROBACION CU-3'!$D$8:$D$16) -> 3
A18: PORCENTAJE : | C18: =C17/9 -> 0.66666667 | D18: =D17/9 -> 0.33333333
A20: DOCUMENTACIÓN
A21: No. | B21: Pregunta | C21: SI | D21: NO
A22: 1 | B22: Aplica un estandar para la documetación de requerimiento? | C22: X
A23: 2 | B23: Cumple con la estructura definida por el estandar? | C23: X
A24: 3 | B24: Utiliza un Glosario de términos normalizado? | C24: X
A25: 4 | B25: Los requerimientos Funcionales estan sujetos a una única interpretación? | D25: x
A26: 5 | B26: El modelo aplicado cumple con la sintaxis? | C26: X
A27: SUMATORIA: | C27: =COUNTA('LISTA COMPROBACION CU-3'!$C$22:$C$26) -> 4 | D27: =COUNTA('LISTA COMPROBACION CU-3'!$D$22:$D$26) -> 1
A28: PORCENTAJE : | C28: =C27/5 -> 0.8 | D28: =D27/5 -> 0.2
A30: NIVEL DE ACUERDO
A31: No. | B31: Pregunta | C31: SI | D31: NO
A32: 1 | B32: Todos los requerimientos han sido acordados con todos los interesados? | C32: x
A33: 2 | B33: Todos los requerimientos modificados han sido acordados por todos los implicados? | C33: x
A34: 3 | B34: Han sido resueltos todos los conflictos conocidos respectos de los requerimientos? | C34: X
A35: SUMATORIA: | C35: =COUNTA('LISTA COMPROBACION CU-3'!$C$32:$C$34) -> 3 | D35: =COUNTA('LISTA COMPROBACION CU-3'!$D$32:$D$34) -> 0
A36: PORCENTAJE : | C36: =C35/3 -> 1 | D36: =D35/3 -> 0
A40: RESUMEN
B41: CONTENIDO | C41: 67
B42: DOCUMENTACIÓN | C42: 80
B43: NIVEL DE ACUERDO | C43: 100

Sheet LISTA COMPROBACION CU-4
B1: SISTEMA: | C1: Pago Seguro Agrotac
B2: FECHA: | C2: 46296
B3: AUTOR: | C3: Andy Conteron
B4: REQUERIMIENTOS EVALUADOS : | C4: CU-4: Importar Datos de Facturación
A6: CONTENIDO
A7: No. | B7: Pregunta | C7: SI | D7: NO
A8: 1 | B8: Todos los requerimientos relevantes se han documentado? | C8: X
A9: 2 | B9: Se han implementado las funciones requeridas? | D9: X
A10: 3 | B10: Existe algún mecanismo que permita seguir el impacto de dicho requerimiento a lo largo del resto de las actividades del ciclo productivo.? | D10: X
A11: 4 | B11: El origen de cada requerimento individual está claro ? | C11: X
A12: 5 | B12: Que tan facil es devolverse a los requerimientos? | C12: X
A13: 6 | B13: Los requerimientos reflejan las necesidades y deseos del cliente? | C13: X
A14: 7 | B14: No hay contradicciones entre los requerimientos? | C14: X
A15: 8 | B15: El requerimiento que se esta especificando contribuye a alcanzar un objetivo definido ? | C15: X
A16: 9 | B16: Existe un proceso acotado (en plazo y presupuesto) que permita determinar que el sistema construido satisface lo descrito en el propio requerimiento? | D16: X
A17: SUMATORIA: | C17: =COUNTA('LISTA COMPROBACION CU-4'!$C$8:$C$16) -> 6 | D17: =COUNTA('LISTA COMPROBACION CU-4'!$D$8:$D$16) -> 3
A18: PORCENTAJE : | C18: =C17/9 -> 0.66666667 | D18: =D17/9 -> 0.33333333
A20: DOCUMENTACIÓN
A21: No. | B21: Pregunta | C21: SI | D21: NO
A22: 1 | B22: Aplica un estandar para la documetación de requerimiento? | C22: X
A23: 2 | B23: Cumple con la estructura definida por el estandar? | C23: X
A24: 3 | B24: Utiliza un Glosario de términos normalizado? | C24: X
A25: 4 | B25: Los requerimientos Funcionales estan sujetos a una única interpretación? | C25: X
A26: 5 | B26: El modelo aplicado cumple con la sintaxis? | C26: X
A27: SUMATORIA: | C27: =COUNTA('LISTA COMPROBACION CU-4'!$C$22:$C$26) -> 5 | D27: =COUNTA('LISTA COMPROBACION CU-4'!$D$22:$D$26) -> 0
A28: PORCENTAJE : | C28: =C27/5 -> 1 | D28: =D27/5 -> 0
A30: NIVEL DE ACUERDO
A31: No. | B31: Pregunta | C31: SI | D31: NO
A32: 1 | B32: Todos los requerimientos han sido acordados con todos los interesados? | C32: X
A33: 2 | B33: Todos los requerimientos modificados han sido acordados por todos los implicados? | C33: X
A34: 3 | B34: Han sido resueltos todos los conflictos conocidos respectos de los requerimientos? | C34: X
A35: SUMATORIA: | C35: =COUNTA('LISTA COMPROBACION CU-4'!$C$32:$C$34) -> 3 | D35: =COUNTA('LISTA COMPROBACION CU-4'!$D$32:$D$34) -> 0
A36: PORCENTAJE : | C36: =C35/3 -> 1 | D36: =D35/3 -> 0
A40: RESUMEN
B41: CONTENIDO | C41: 67
B42: DOCUMENTACIÓN | C42: 100
B43: NIVEL DE ACUERDO | C43: 100

Sheet LISTA COMPROBACION CU-5
B1: SISTEMA: | C1: Pago Seguro Agrotac
B2: FECHA: | C2: 46296
B3: AUTOR: | C3: Juda Grijalva
B4: REQUERIMIENTOS EVALUADOS : | C4: CU-5: Gestionar créditos otorgados
A6: CONTENIDO
A7: No. | B7: Pregunta | C7: SI | D7: NO
A8: 1 | B8: Todos los requerimientos relevantes se han documentado? | C8: X
A9: 2 | B9: Se han implementado las funciones requeridas? | D9: X
A10: 3 | B10: Existe algún mecanismo que permita seguir el impacto de dicho requerimiento a lo largo del resto de las actividades del ciclo productivo.? | C10: x
A11: 4 | B11: El origen de cada requerimento individual está claro ? | C11: X
A12: 5 | B12: Que tan facil es devolverse a los requerimientos? | C12: X
A13: 6 | B13: Los requerimientos reflejan las necesidades y deseos del cliente? | C13: X
A14: 7 | B14: No hay contradicciones entre los requerimientos? | D14: x
A15: 8 | B15: El requerimiento que se esta especificando contribuye a alcanzar un objetivo definido ? | C15: X
A16: 9 | B16: Existe un proceso acotado (en plazo y presupuesto) que permita determinar que el sistema construido satisface lo descrito en el propio requerimiento? | D16: X
A17: SUMATORIA: | C17: =COUNTA('LISTA COMPROBACION CU-5'!$C$8:$C$16) -> 6 | D17: =COUNTA('LISTA COMPROBACION CU-5'!$D$8:$D$16) -> 3
A18: PORCENTAJE : | C18: =C17/9 -> 0.66666667 | D18: =D17/9 -> 0.33333333
A20: DOCUMENTACIÓN
A21: No. | B21: Pregunta | C21: SI | D21: NO
A22: 1 | B22: Aplica un estandar para la documetación de requerimiento? | C22: X
A23: 2 | B23: Cumple con la estructura definida por el estandar? | C23: X
A24: 3 | B24: Utiliza un Glosario de términos normalizado? | C24: X
A25: 4 | B25: Los requerimientos Funcionales estan sujetos a una única interpretación? | C25: X
A26: 5 | B26: El modelo aplicado cumple con la sintaxis? | D26: x
A27: SUMATORIA: | C27: =COUNTA('LISTA COMPROBACION CU-5'!$C$22:$C$26) -> 4 | D27: =COUNTA('LISTA COMPROBACION CU-5'!$D$22:$D$26) -> 1
A28: PORCENTAJE : | C28: =C27/5 -> 0.8 | D28: =D27/5 -> 0.2
A30: NIVEL DE ACUERDO
A31: No. | B31: Pregunta | C31: SI | D31: NO
A32: 1 | B32: Todos los requerimientos han sido acordados con todos los interesados? | C32: X
A33: 2 | B33: Todos los requerimientos modificados han sido acordados por todos los implicados? | C33: X
A34: 3 | B34: Han sido resueltos todos los conflictos conocidos respectos de los requerimientos? | C34: X
A35: SUMATORIA: | C35: =COUNTA('LISTA COMPROBACION CU-5'!$C$32:$C$34) -> 3 | D35: =COUNTA('LISTA COMPROBACION CU-5'!$D$32:$D$34) -> 0
A36: PORCENTAJE : | C36: =C35/3 -> 1 | D36: =D35/3 -> 0
A40: RESUMEN
B41: CONTENIDO | C41: 67
B42: DOCUMENTACIÓN | C42: 80
B43: NIVEL DE ACUERDO | C43: 100

Sheet LISTA COMPROBACION CU-6
B1: SISTEMA: | C1: Pago Seguro Agrotac
B2: FECHA: | C2: 46296
B3: AUTOR: | C3: Andy Conteron
B4: REQUERIMIENTOS EVALUADOS : | C4: CU-6: Generar reportes de pagos y créditos
A6: CONTENIDO
A7: No. | B7: Pregunta | C7: SI | D7: NO
A8: 1 | B8: Todos los requerimientos relevantes se han documentado? | C8: X
A9: 2 | B9: Se han implementado las funciones requeridas? | D9: X
A10: 3 | B10: Existe algún mecanismo que permita seguir el impacto de dicho requerimiento a lo largo del resto de las actividades del ciclo productivo.? | C10: X
A11: 4 | B11: El origen de cada requerimento individual está claro ? | C11: X
A12: 5 | B12: Que tan facil es devolverse a los requerimientos? | C12: X
A13: 6 | B13: Los requerimientos reflejan las necesidades y deseos del cliente? | C13: X
A14: 7 | B14: No hay contradicciones entre los requerimientos? | D14: X
A15: 8 | B15: El requerimiento que se esta especificando contribuye a alcanzar un objetivo definido ? | C15: X
A16: 9 | B16: Existe un proceso acotado (en plazo y presupuesto) que permita determinar que el sistema construido satisface lo descrito en el propio requerimiento? | D16: X
A17: SUMATORIA: | C17: =COUNTA('LISTA COMPROBACION CU-6'!$C$8:$C$16) -> 6 | D17: =COUNTA('LISTA COMPROBACION CU-6'!$D$8:$D$16) -> 3
A18: PORCENTAJE : | C18: =C17/9 -> 0.66666667 | D18: =D17/9 -> 0.33333333
A20: DOCUMENTACIÓN
A21: No. | B21: Pregunta | C21: SI | D21: NO
A22: 1 | B22: Aplica un estandar para la documetación de requerimiento? | C22: X
A23: 2 | B23: Cumple con la estructura definida por el estandar? | C23: X
A24: 3 | B24: Utiliza un Glosario de términos normalizado? | C24: X
A25: 4 | B25: Los requerimientos Funcionales estan sujetos a una única interpretación? | D25: X
A26: 5 | B26: El modelo aplicado cumple con la sintaxis? | C26: X
A27: SUMATORIA: | C27: =COUNTA('LISTA COMPROBACION CU-6'!$C$22:$C$26) -> 4 | D27: =COUNTA('LISTA COMPROBACION CU-6'!$D$22:$D$26) -> 1
A28: PORCENTAJE : | C28: =C27/5 -> 0.8 | D28: =D27/5 -> 0.2
A30: NIVEL DE ACUERDO
A31: No. | B31: Pregunta | C31: SI | D31: NO
A32: 1 | B32: Todos los requerimientos han sido acordados con todos los interesados? | C32: X
A33: 2 | B33: Todos los requerimientos modificados han sido acordados por todos los implicados? | C33: X
A34: 3 | B34: Han sido resueltos todos los conflictos conocidos respectos de los requerimientos? | C34: X
A35: SUMATORIA: | C35: =COUNTA('LISTA COMPROBACION CU-6'!$C$32:$C$34) -> 3 | D35: =COUNTA('LISTA COMPROBACION CU-6'!$D$32:$D$34) -> 0
A36: PORCENTAJE : | C36: =C35/3 -> 1 | D36: =D35/3 -> 0
A40: RESUMEN
B41: CONTENIDO | C41: 67
B42: DOCUMENTACIÓN | C42: 80
B43: NIVEL DE ACUERDO | C43: 100

Sheet LISTA COMPROBACION CU-7
B1: SISTEMA: | C1: Pago Seguro Agrotac
B2: FECHA: | C2: 46296
B3: AUTOR: | C3: César Luis Galarza Villalva
B4: REQUERIMIENTOS EVALUADOS : | C4: CU-7: Revisar estado de cuenta del cliente
A6: CONTENIDO
A7: No. | B7: Pregunta | C7: SI | D7: NO
A8: 1 | B8: Todos los requerimientos relevantes se han documentado? | C8: X
A9: 2 | B9: Se han implementado las funciones requeridas? | D9: X
A10: 3 | B10: Existe algún mecanismo que permita seguir el impacto de dicho requerimiento a lo largo del resto de las actividades del ciclo productivo.? | C10: X
A11: 4 | B11: El origen de cada requerimento individual está claro ? | C11: X
A12: 5 | B12: Que tan facil es devolverse a los requerimientos? | C12: X
A13: 6 | B13: Los requerimientos reflejan las necesidades y deseos del cliente? | C13: X
A14: 7 | B14: No hay contradicciones entre los requerimientos? | D14: X
A15: 8 | B15: El requerimiento que se esta especificando contribuye a alcanzar un objetivo definido ? | C15: X
A16: 9 | B16: Existe un proceso acotado (en plazo y presupuesto) que permita determinar que el sistema construido satisface lo descrito en el propio requerimiento? | D16: X
A17: SUMATORIA: | C17: =COUNTA('LISTA COMPROBACION CU-7'!$C$8:$C$16) -> 6 | D17: =COUNTA('LISTA COMPROBACION CU-7'!$D$8:$D$16) -> 3
A18: PORCENTAJE : | C18: =C17/9 -> 0.66666667 | D18: =D17/9 -> 0.33333333
A20: DOCUMENTACIÓN
A21: No. | B21: Pregunta | C21: SI | D21: NO
A22: 1 | B22: Aplica un estandar para la documetación de requerimiento? | C22: X
A23: 2 | B23: Cumple con la estructura definida por el estandar? | C23: X
A24: 3 | B24: Utiliza un Glosario de términos normalizado? | C24: X
A25: 4 | B25: Los requerimientos Funcionales estan sujetos a una única interpretación? | D25: X
A26: 5 | B26: El modelo aplicado cumple con la sintaxis? | C26: X
A27: SUMATORIA: | C27: =COUNTA('LISTA COMPROBACION CU-7'!$C$22:$C$26) -> 4 | D27: =COUNTA('LISTA COMPROBACION CU-7'!$D$22:$D$26) -> 1
A28: PORCENTAJE : | C28: =C27/5 -> 0.8 | D28: =D27/5 -> 0.2
A30: NIVEL DE ACUERDO
A31: No. | B31: Pregunta | C31: SI | D31: NO
A32: 1 | B32: Todos los requerimientos han sido acordados con todos los interesados? | C32: X
A33: 2 | B33: Todos los requerimientos modificados han sido acordados por todos los implicados? | C33: X
A34: 3 | B34: Han sido resueltos todos los conflictos conocidos respectos de los requerimientos? | C34: X
A35: SUMATORIA: | C35: =COUNTA('LISTA COMPROBACION CU-7'!$C$32:$C$34) -> 3 | D35: =COUNTA('LISTA COMPROBACION CU-7'!$D$32:$D$34) -> 0
A36: PORCENTAJE : | C36: =C35/3 -> 1 | D36: =D35/3 -> 0
A40: RESUMEN
B41: CONTENIDO | C41: 67
B42: DOCUMENTACIÓN | C42: 80
B43: NIVEL DE ACUERDO | C43: 100

Sheet LISTA COMPROBACION CU-8
B1: SISTEMA: | C1: Pago Seguro Agrotac
B2: FECHA: | C2: 46296
B3: AUTOR: | C3: Juda Benhur Grijalva Ñacato
B4: REQUERIMIENTOS EVALUADOS : | C4: CU-8: Gestionar notificaciones
A6: CONTENIDO
A7: No. | B7: Pregunta | C7: SI | D7: NO
A8: 1 | B8: Todos los requerimientos relevantes se han documentado? | C8: X
A9: 2 | B9: Se han implementado las funciones requeridas? | D9: X
A10: 3 | B10: Existe algún mecanismo que permita seguir el impacto de dicho requerimiento a lo largo del resto de las actividades del ciclo productivo.? | C10: X
A11: 4 | B11: El origen de cada requerimento individual está claro ? | C11: X
A12: 5 | B12: Que tan facil es devolverse a los requerimientos? | C12: X
A13: 6 | B13: Los requerimientos reflejan las necesidades y deseos del cliente? | C13: X
A14: 7 | B14: No hay contradicciones entre los requerimientos? | C14: X
A15: 8 | B15: El requerimiento que se esta especificando contribuye a alcanzar un objetivo definido ? | C15: X
A16: 9 | B16: Existe un proceso acotado (en plazo y presupuesto) que permita determinar que el sistema construido satisface lo descrito en el propio requerimiento? | C16: X
A17: SUMATORIA: | C17: =COUNTA('LISTA COMPROBACION CU-8'!$C$8:$C$16) -> 8 | D17: =COUNTA('LISTA COMPROBACION CU-8'!$D$8:$D$16) -> 1
A18: PORCENTAJE : | C18: =C17/9 -> 0.88888889 | D18: =D17/9 -> 0.11111111
A20: DOCUMENTACIÓN
A21: No. | B21: Pregunta | C21: SI | D21: NO
A22: 1 | B22: Aplica un estandar para la documetación de requerimiento? | C22: X
A23: 2 | B23: Cumple con la estructura definida por el estandar? | C23: X
A24: 3 | B24: Utiliza un Glosario de términos normalizado? | C24: X
A25: 4 | B25: Los requerimientos Funcionales estan sujetos a una única interpretación? | C25: X
A26: 5 | B26: El modelo aplicado cumple con la sintaxis? | C26: X
A27: SUMATORIA: | C27: =COUNTA('LISTA COMPROBACION CU-8'!$C$22:$C$26) -> 5 | D27: =COUNTA('LISTA COMPROBACION CU-8'!$D$22:$D$26) -> 0
A28: PORCENTAJE : | C28: =C27/5 -> 1 | D28: =D27/5 -> 0
A30: NIVEL DE ACUERDO
A31: No. | B31: Pregunta | C31: SI | D31: NO
A32: 1 | B32: Todos los requerimientos han sido acordados con todos los interesados? | C32: X
A33: 2 | B33: Todos los requerimientos modificados han sido acordados por todos los implicados? | C33: X
A34: 3 | B34: Han sido resueltos todos los conflictos conocidos respectos de los requerimientos? | C34: X
A35: SUMATORIA: | C35: =COUNTA('LISTA COMPROBACION CU-8'!$C$32:$C$34) -> 3 | D35: =COUNTA('LISTA COMPROBACION CU-8'!$D$32:$D$34) -> 0
A36: PORCENTAJE : | C36: =C35/3 -> 1 | D36: =D35/3 -> 0
A40: RESUMEN
B41: CONTENIDO | C41: 89
B42: DOCUMENTACIÓN | C42: 100
B43: NIVEL DE ACUERDO | C43: 100

Sheet RECOMENDACIONES - CU-1
A1: PREGUNTA | B1: RECOMENDACIÓN
A2: ¿Existe un proceso acotado (en plazo y presupuesto) que permita determinar que el sistema construido satisface lo descrito en el propio requerimiento? | B2: Establecer un proceso formal de verificación y validación acotado en plazo y recursos. Debe incluir responsables asignados, fechas clave, criterios de aceptación objetivos y el diseño de casos de prueba con usuarios finales, asegurando la documentación de evidencias y la trazabilidad requerimiento-prueba para comprobar objetivamente el cumplimiento del sistema.
A3: ¿Los requerimientos Funcionales estan sujetos a una única interpretación? que permitan medir objetivamente el cumplimiento del requisito? | B3: Normalizar la redacción del requerimiento eliminando ambigüedades y asegurando consistencia técnica con el glosario. Para garantizar su cumplimiento objetivo, se deben establecer criterios de aceptación verificables y realizar una sesión de validación clave antes de su paso a desarrollo.

Sheet RECOMENDACIONES - CU-2
A1: PREGUNTA | B1: RECOMENDACIÓN
A2: ¿Se han incorporado todos los requerimientos de nivel cero al sistema? | B2: Se recomienda establecer un proceso formal de gestión de cambios que incluya el registro, revisión e incorporación de cada sugerencia recibida por parte del tutor o cliente, asegurando que los requisitos estén siempre actualizados, reflejen las expectativas reales y eviten ambigüedades o malentendidos en etapas posteriores del desarrollo.
A3: ¿Se mantiene la coherencia con otros requisitos del sistema y utiliza términos o definiciones de forma uniforme a lo largo del documento? | B3: Aunque el requisito mantiene coherencia con los demás y utiliza los términos de forma uniforme, se recomienda revisar la redacción para eliminar palabras redundantes que no aportan valor, donde una redacción más concisa mejora la claridad del requisito.
A4: ¿Se han definido criterios de aceptación y casos de prueba que permitan medir objetivamente el cumplimiento del requisito? | B4: Elaborar una lista de Criterios de Aceptación en formato Given-When-Then, asociada a pruebas unitarias o de aceptación automatizadas, de modo que cada criterio quede cubierto por al menos un caso de prueba.
A5: ¿Todos los requerimientos han sido acordados con todos los interesados? | B5: Se recomienda realizar sesiones de validación y consenso con todos los interesados clave antes de cerrar la especificación de requerimientos, esto asegurará que los requerimientos reflejen las necesidades puntuales.

Sheet RECOMENDACIONES - CU-3
A1: PREGUNTA | B1: RECOMENDACIÓN
A2: ¿Cuál es el orden específico de imputación de los abonos y qué métodos de pago se permitirán en el sistema? | B2: Documentar e incorporar de inmediato el orden de prelación de pagos (por ejemplo: si el abono cubre primero intereses de mora, luego intereses corrientes y finalmente el capital). Asimismo, se deben detallar explícitamente los métodos de pago aceptados y las diferencias operativas entre un pago presencial y uno en línea.
A3: ¿Cómo se reestructurará el catálogo de casos de uso para eliminar la duplicidad de funciones con CU-2 y CU-5? | B3: Refactorizar el diseño de los casos de uso para evitar código duplicado y conflictos lógicos. Se sugiere que las funciones comunes (como el cálculo de saldos/intereses y la generación de comprobantes) se centralicen en un único componente o servicio reusable, delimitando claramente qué le corresponde a CU-3 y qué a CU-5 (pagos en línea).
A4: ¿Bajo qué escenarios y criterios de aceptación se validará el correcto funcionamiento del recálculo de saldos y el manejo de excepciones? | B4: Diseñar una matriz de casos de prueba exhaustiva que incluya escenarios felices y lógicas de excepción (por ejemplo: qué ocurre si el crédito está inactivo, si el monto ingresado es negativo o cero, o si se cae la conexión durante un pago). Esta matriz debe acompañarse de un plan de validación con fechas y responsables asignados.
A5: ¿Cuál es el cronograma estimado para el desarrollo de la lógica de aplicación de abonos y la actualización de saldos en tiempo real? | B5: Priorizar el desarrollo de este requisito en el backlog, dado que está catalogado como un requerimiento de "nivel 0 crítico" para el control de cartera de El Granito de AGROTAC. Se debe asegurar que la base de datos soporte la concurrencia necesaria para la actualización en tiempo real.

Sheet RECOMENDACIONES - CU-4
A1: PREGUNTA | B1: RECOMENDACIÓN
A2: ¿Se han implementado las funciones requeridas? | B2: Implementar el módulo de importación de datos de facturación con soporte para los formatos definidos y evidencia de funcionamiento.
A3: ¿Existe algún mecanismo que permita seguir el impacto de dicho requerimiento a lo largo del resto de las actividades del ciclo productivo? | B3: Incorporar CU-4 a una matriz de trazabilidad que relacione origen, SRS, diseño, implementación y pruebas.
A4: ¿Existe un proceso acotado que permita determinar que el sistema construido satisface lo descrito en el propio requerimiento? | B4: Implementar un plan de validación y verificación que incluya: Actividades de prueba con fechas y responsables definidos Presupuesto estimado para pruebas y revisiones
A5: ¿Existe un proceso acotado (en plazo y presupuesto) que permita determinar que el sistema construido satisface lo descrito en el propio requerimiento? | B5: Definir un plan de verificación para RF-4 con archivos válidos e inválidos, duplicados, inconsistencias y criterios de aceptación medibles.

Sheet RECOMENDACIONES - CU-5
A1: PREGUNTA | B1: RECOMENDACIÓN
A2: ¿Se han implementado las funciones requeridas? | B2: Completar la implementación de CU-5 (gestión de créditos otorgados), incluyendo otorgamiento, consulta y actualización de créditos, con evidencia de funcionamiento.
A3: ¿No hay contradicciones entre los requerimientos? | B3: Documentar formalmente en CU-5 la función «Editar plan de pagos existente» o retirarla del diseño si no pertenece al alcance vigente.
A4: ¿Existe un proceso acotado (en plazo y presupuesto) que permita determinar que el sistema construido satisface lo descrito en el propio requerimiento? | B4: Definir pruebas para otorgamiento de crédito, consultas, pagos asociados y generación de certificados, incluyendo casos alternos.
A5: ¿Los requerimientos funcionales están sujetos a una única interpretación? | B5: Refinar reglas, precondiciones y resultados de CU-5 para evitar interpretaciones distintas entre análisis, diseño e implementación.

Sheet RECOMENDACIONES - CU-6
A1: PREGUNTA | B1: RECOMENDACIÓN
A2: ¿Se han implementado las funciones requeridas? | B2: Completar y evidenciar la implementación de reportes por cliente, fechas, morosidad y consultas asociadas.
A3: ¿No hay contradicciones entre los requerimientos? | B3: Alinear la función «Visualizar auditoría de acciones» con RF-6, documentándola en el requisito o ajustando el diagrama para eliminar la inconsistencia.
A4: ¿Existe un proceso acotado (en plazo y presupuesto) que permita determinar que el sistema construido satisface lo descrito en el propio requerimiento? | B4: Definir pruebas de reportes para rangos de fechas, clientes sin movimientos, ausencia de morosidad y resultados vacíos.
A5: ¿Los requerimientos funcionales están sujetos a una única interpretación? | B5: Precisar entradas, filtros, salidas y formatos esperados de cada reporte para asegurar una interpretación única.

Sheet RECOMENDACIONES - CU-7
A1: PREGUNTA | B1: RECOMENDACIÓN
A2: ¿Se han implementado y verificado todas las funciones requeridas para la consulta del estado de cuenta? | B2: Completar y documentar formalmente las evidencias de implementación de la consulta de estado de cuenta. Se deben incluir y verificar los componentes esenciales: saldo actualizado, detalle de cuotas, registro cronológico de pagos e historial de movimientos, asegurando la captura de evidencias mediante pruebas de usuario final.
A3: ¿Se ha garantizado la no contradicción y la coherencia de CU-7 frente a otros requerimientos del sistema? | B3: Delimitar y formalizar el alcance de CU-7 respecto a CU-5, relativo a la gestión de créditos, y CU-6, enfocado en reportes de pagos y créditos. Es necesario establecer una matriz de trazabilidad y dependencias que defina con claridad qué datos y transacciones corresponden a la consulta operativa del cliente y cuáles a la gestión crediticia o generación de informes administrativos.
A4: ¿Existe un proceso formal, acotado en plazo y presupuesto, para validar que el sistema cumple con lo especificado? | B4: Definir e implementar un plan de pruebas y validación acotado en tiempo y recursos. El plan debe contemplar escenarios clave como el resumen de cuenta, la aplicación de filtros de búsqueda, la visualización de cuentas sin movimientos y la exportación de comprobantes, estableciendo responsables, criterios de aceptación medibles y registro de evidencias para evitar desviaciones.
A5: ¿Los requerimientos funcionales y reglas de negocio de CU-7 admiten una única interpretación verificable? | B5: Especificar detalladamente el requisito mediante diagramas de estado, reglas de negocio precisas y flujos de interacción básicos, alternos y de excepción. Esto eliminará ambigüedades técnicas, asegurará coherencia con el glosario del proyecto y proporcionará criterios de aceptación verificables antes de su desarrollo.

Sheet RECOMENDACIONES - CU-8
A1: PREGUNTA | B1: RECOMENDACIÓN
A2: ¿Existen casos de prueba definidos que permitan verificar el cumplimiento del requisito? | B2: Se debe elaborar un conjunto completo de casos de prueba para cada sub-requisito del CU-8: CU-8.1: Casos de prueba que verifiquen la emisión de notificaciones cuando un crédito alcanza su fecha de vencimiento, incluyendo escenarios con diferentes tipos de créditos y fechas. CU-8.2: Casos de prueba que validen la generación de notificaciones preventivas exactamente 3 días antes del vencimiento, considerando días hábiles, fines de semana y fechas especiales. CU-8.3: Casos de prueba que confirmen la emisión de alertas para pagos vencidos sin abonos registrados, verificando la correcta identificación de deudas morosas.
A3: ¿El requisito ha sido implementado y está funcional en el sistema? | B3: Se recomienda iniciar el proceso de implementación del CU-8 según lo planificado en el presupuesto del proyecto. Es necesario: Asignar los recursos técnicos necesarios para el desarrollo de las tres funcionalidades de notificación (CU-8.1, CU-8.2, CU-8.3). Realizar pruebas unitarias e integrales durante el desarrollo para garantizar el correcto funcionamiento antes del despliegue final. Coordinar con el cliente una demostración del módulo una vez completada la implementación para validar que cumple con sus expectativas.
